graph_hypothesis/__init__.py
graph_hypothesis/axb_motifs.py
graph_hypothesis/core.py
graph_hypothesis/hypothesis_tester.py
graph_hypothesis/interactions.py
graph_hypothesis/interactions_proportion.py
graph_hypothesis/permute_graph.py
graph_hypothesis/shortest_path.py
graph_hypothesis/validate_graph.py
graph_hypothesis-0.1.1.dist-info/METADATA
graph_hypothesis-0.1.1.dist-info/WHEEL
graph_hypothesis-0.1.1.dist-info/top_level.txt
graph_hypothesis-0.1.1.dist-info/RECORD
