Metadata-Version: 2.4
Name: graph_hypothesis
Version: 0.1.1
Summary: A Python package for statistical analysis on graphs using permutation tests.
Author-email: V Subrahmanya Raghu Ram Kishore Parupudi <pvsrrkishore@gmail.com>
Keywords: graph theory,network analysis,statistics,machine learning,data science
Classifier: Programming Language :: Python :: 3
Classifier: License :: OSI Approved :: MIT License
Classifier: Operating System :: OS Independent
Classifier: Development Status :: 3 - Alpha
Classifier: Intended Audience :: Science/Research
Classifier: Topic :: Scientific/Engineering :: Mathematics
Classifier: Topic :: Scientific/Engineering :: Artificial Intelligence
Requires-Python: >=3.8
Requires-Dist: networkx>=2.5
Requires-Dist: numpy>=1.20
Requires-Dist: tqdm>=4.0
Provides-Extra: dev
Requires-Dist: pytest>=7.0; extra == "dev"
Requires-Dist: pytest-cov>=3.0; extra == "dev"
